./.gitignore
./PKG-INFO
./README.md
./pyproject.toml
./requirements.txt
./analyzer/__init__.py
./analyzer/analyze.py
./analyzer/files.py
./analyzer/llm.py
./cli_tools/__init__.py
./cli_tools/cli.py
./config/__init__.py
./config/analyzer_config.py
./config/logger.py
./config/prompts.py
./config/schemas.py
./config/settings.py
ai_readme_generator_cli-0.1.3.dist-info/METADATA
ai_readme_generator_cli-0.1.3.dist-info/WHEEL
ai_readme_generator_cli-0.1.3.dist-info/entry_points.txt
ai_readme_generator_cli-0.1.3.dist-info/RECORD
