Metadata-Version: 2.4
Name: ai-readme-generator-cli
Version: 0.1.3
Summary: A stateful AI-powered README generator using LangGraph and multi-model orchestration.
Author-email: Akshat Sharma <akshatsharmasde@gmail.com>
License: MIT
Keywords: ai,automation,gemini,langchain,langgraph,openai,readme
Requires-Python: >=3.9
Requires-Dist: langchain-anthropic<2.0,>=1.3
Requires-Dist: langchain-core<2.0,>=1.2
Requires-Dist: langchain-google-genai<5.0,>=4.2
Requires-Dist: langchain-openai<2.0,>=1.1
Requires-Dist: langchain<2.0,>=1.2
Requires-Dist: langgraph<2.0,>=1.0
Requires-Dist: pydantic-settings<3.0,>=2.12
Requires-Dist: pydantic<3.0,>=2.10
Requires-Dist: python-dotenv<2.0,>=1.2
Requires-Dist: requests<3.0,>=2.32
Requires-Dist: tiktoken<1.0,>=0.12
